<?xml version="1.0" encoding="UTF-8"?>
<tns:Transaction MODULE_NAME="ESTATE" PROCESS_NAME="GuestHouse MntStatus" xmlns:tns="http://www.example.org/transactionSchema" xmlns:xsi="http://www.w3.org/2001/XMLSchema-instance" xsi:schemaLocation="http://www.example.org/transactionSchema transactionSchema.xsd ">
<OPR ID="1" NAME="INSERT" BLOCK_SIZE="1" QRY_TOT_SIZE="1" TRN_MGMT="Y">
  <BLOCK ID="1" QRY_SIZE="1" ROWS_INS="M" MANDATORY="Y">
	<QRY ID="1" COL_SIZE="16">
	 INSERT INTO EST_GUEST_HOUSE_MNT_STATUS_DTL (NUM_HOSPITAL_ID,NUM_GUEST_HOUSE_ID,NUM_SERVICE_AGENCY_TYPE_ID,NUM_SERVICE_AGENCY_ID,STR_DESCRIPTION,STR_MAINTENANCE_DESC,STR_MAINTENANCE_STATUS,DT_FROM_DATE,DT_TO_DATE,GDT_EFFECT_DATE,GDT_ENTRY_DATE,GNUM_ISVALID,GNUM_SEAT_ID,GNUM_SLNO_S_A_T,GNUM_SLNO_S_A,GNUM_SLNO_G) VALUES (?,?,?,?,?,?,?,?,?,?,?,?,?,?,?,?)
	</QRY>
	</BLOCK>
   </OPR>
<OPR ID="2" NAME="UPDATE" BLOCK_SIZE="1" QRY_TOT_SIZE="1" TRN_MGMT="Y">
  <BLOCK ID="1" QRY_SIZE="1" ROWS_INS="M" MANDATORY="Y">
	<QRY ID="1" COL_SIZE="1">
	 DELETE FROM  EST_GUEST_HOUSE_MNT_STATUS_DTL A WHERE A.NUM_GUEST_HOUSE_ID=?
	</QRY>
   </BLOCK>
   </OPR>
<OPR ID="3" NAME="INSERTION FOR UPDATE" BLOCK_SIZE="1" QRY_TOT_SIZE="1" TRN_MGMT="Y">
  <BLOCK ID="1" QRY_SIZE="1" ROWS_INS="M" MANDATORY="Y">
	<QRY ID="1" COL_SIZE="18">
	 INSERT INTO EST_GUEST_HOUSE_MNT_STATUS_DTL (NUM_HOSPITAL_ID,NUM_GUEST_HOUSE_ID,NUM_SERVICE_AGENCY_TYPE_ID,NUM_SERVICE_AGENCY_ID,STR_DESCRIPTION,STR_MAINTENANCE_DESC,STR_MAINTENANCE_STATUS,DT_FROM_DATE,DT_TO_DATE,GDT_EFFECT_DATE,GDT_ENTRY_DATE,GNUM_ISVALID,GNUM_SEAT_ID,GNUM_SLNO_S_A_T,GNUM_SLNO_S_A,GNUM_SLNO_G,GDT_LSTMOD_DATE,GDT_LSTMOD_SEATID) VALUES (?,?,?,?,?,?,?,?,?,?,?,?,?,?,?,?,?,?)
	</QRY>
	</BLOCK>
   </OPR>
<OPR ID="4" NAME="DELETE" BLOCK_SIZE="1" QRY_TOT_SIZE="1" TRN_MGMT="Y">
  <BLOCK ID="1" QRY_SIZE="1" ROWS_INS="S" MANDATORY="Y">
	<QRY ID="1" COL_SIZE="1">
	 UPDATE EST_GUEST_HOUSE_MNT_STATUS_DTL SET GNUM_ISVALID=0 WHERE NUM_GUEST_HOUSE_ID=? AND GNUM_ISVALID=1
	</QRY>
   </BLOCK>
</OPR>
   
   
</tns:Transaction>
