<?xml version="1.0" encoding="UTF-8"?>

<tns:Transaction MODULE_NAME="HR" PROCESS_NAME="Increment" xmlns:tns="http://www.example.org/transactionSchema" xmlns:xsi="http://www.w3.org/2001/XMLSchema-instance" xsi:schemaLocation="http://www.example.org/transactionSchema transactionSchema.xsd ">

<OPR ID="1" NAME="INSERT" BLOCK_SIZE="1" QRY_TOT_SIZE="1" TRN_MGMT="N">
<BLOCK ID="1" QRY_SIZE="3" ROWS_INS="S" MANDATORY="Y">
<QRY ID="1" COL_SIZE="23">
INSERT INTO PIST_INCREMENT_DTL (STR_EMP_NO,NUM_SL_NO,STR_ORDER_NO,DT_ORDER_DATE,STR_INCREMENT_TYPE,NUM_OLD_BASIC_PAY,DT_INC_DUE_DATE,DT_NEXT_INC_DATE,NUM_NEW_BASIC_PAY,DT_BASIC_EFF_DATE,STR_PAY_SCALE_CATEGORY, STR_PAY_SCALE_TYPE, STR_PAY_BAND, STR_PAY_CODE, NUM_GRADE_PAY, GDT_LSTMOD_DATE, GNUM_LSTMOD_SEATID, GDT_EFFECT_DATE, GDT_ENTRY_DATE, GNUM_ISVALID, GNUM_SEAT_ID,GNUM_HOSPITAL_CODE) VALUES (?,?,?,?,?,?,?,add_months(?,?),?,?,?,?,?,?,?,?,?,?,?,?,?,?)
</QRY>

<QRY ID="2" COL_SIZE="10">
Update PIST_EMP_CUR_DETAIL_DTL A Set A.NUM_CUR_BASIC_PAY=?, A.DT_BASIC_EFF_DATE=?, A.DT_NEXT_INC_DATE=add_months(?,?), A.STR_EVENT_CODE=?, A.DT_EVENT_DATE=?, A.GDT_LSTMOD_DATE=?, A.GNUM_LSTMOD_SEATID=? where A.STR_EMP_NO=? AND A.GNUM_HOSPITAL_CODE=?
</QRY>

<QRY ID="3" COL_SIZE="27">
INSERT INTO PIST_EMP_PAYFIXATION_DTL (STR_EMP_NUMBER,NUM_SL_NO,STR_REASON_FOR_PAYFIX,STR_ORDER_NUMBER,DT_ORDER_DATE,STR_OLD_PAY_SCALE_CATEGORY,STR_OLD_PAY_SCALE_TYPE,STR_OLD_PAY_CODE,STR_OLD_PAY_BAND,NUM_OLD_GRADE_PAY,NUM_OLD_CUR_BASIC_PAY, STR_NEW_PAY_SCALE_CATEGORY, STR_NEW_PAY_SCALE_TYPE,STR_NEW_PAY_CODE,STR_NEW_PAY_BAND,NUM_NEW_GRADE_PAY,NUM_NEW_CUR_BASIC_PAY,DT_BASIC_EFFECT_DATE,DT_NEXT_INC_DATE, GDT_LSTMOD_DATE, GNUM_LSTMOD_SEATID, GDT_EFFECT_DATE, GDT_ENTRY_DATE, GNUM_ISVALID, GNUM_SEAT_ID,GNUM_HOSPITAL_CODE) VALUES (?,?,?,?,?,?,?,?,?,?,?,?,?,?,?,?,?,?,add_months(?,?),?,?,?,?,?,?,?)
</QRY>

</BLOCK>
</OPR>


<OPR ID="2" NAME="UPDATE" BLOCK_SIZE="1" QRY_TOT_SIZE="1" TRN_MGMT="N">
<BLOCK ID="1" QRY_SIZE="1" ROWS_INS="S" MANDATORY="Y">
<QRY ID="1" COL_SIZE="20">
Not in use
UPDATE PIST_INCREMENT_DTL A SET A.STR_EMP_NO=?,A.NUM_SL_NO=?,A.STR_ORDER_NO=?,A.DT_ORDER_DATE=?,A.STR_INCREMENT_TYPE=?,A.NUM_OLD_BASIC_PAY=?,A.DT_INC_DUE_DATE=?,A.DT_NEXT_INC_DATE=?,A.NUM_NEW_BASIC_PAY=?,DT_BASIC_EFF_DATE=?,A.NUM_PAY_ID=?, A.GDT_LSTMOD_DATE=?, A.GNUM_LSTMOD_SEATID=?, A.GDT_EFFECT_DATE=?, A.GDT_ENTRY_DATE=?, A.GNUM_ISVALID=?, A.GNUM_SEAT_ID=?, A.GNUM_HOSPITAL_CODE=? WHERE A.STR_EMP_NO=? and A.NUM_SL_NO=?  AND A.GNUM_HOSPITAL_CODE=?
</QRY>
</BLOCK>
</OPR>


<OPR ID="3" NAME="DELETE" BLOCK_SIZE="1" QRY_TOT_SIZE="1" TRN_MGMT="N">
<BLOCK ID="1" QRY_SIZE="1" ROWS_INS="S" MANDATORY="Y">
<QRY ID="1" COL_SIZE="6">
Not in use
UPDATE PIST_INCREMENT_DTL A SET A.GNUM_ISVALID=0 WHERE  A.STR_EMP_NO=? AND A.GNUM_HOSPITAL_CODE=?
</QRY>
</BLOCK>
</OPR>


</tns:Transaction>
